kin_tokenizer/__init__.py
kin_tokenizer/tokenizer.py
kin_tokenizer/utils.py
kin_tokenizer/version.py
kin_tokenizer/data/kin_tokenizer.pkl
kin_tokenizer-3.3.2.dist-info/METADATA
kin_tokenizer-3.3.2.dist-info/WHEEL
kin_tokenizer-3.3.2.dist-info/top_level.txt
kin_tokenizer-3.3.2.dist-info/RECORD
