Metadata-Version: 2.1
Name: kin-tokenizer
Version: 3.3.2
Summary: Kinyarwanda tokenizer for encoding and decoding Kinyarwanda language text
Home-page: https://github.com/Nschadrack/Kin-Tokenizer
Author: Schadrack Niyibizi
Author-email: niyibizischadrack@gmail.com
Keywords: Tokenizer,Kinyarwanda,KinGPT
Classifier: Programming Language :: Python :: 3
Classifier: Operating System :: OS Independent
Requires-Python: >=3.7
Requires-Dist: regex >=2024.7.24
Requires-Dist: setuptools >=72.2.0
